dochint/__init__.py
dochint/__main__.py
dochint/_cli.py
dochint/_helper.py
dochint/_macros.py
dochint/deferrable_string.py
dochint/exceptions.py
dochint/macro.py
dochint/processor.py
dochint/state.py
dochint-1.0.1.dist-info/licenses/LICENSE
dochint-1.0.1.dist-info/licenses/LICENSE.Apache-2.0
dochint-1.0.1.dist-info/licenses/LICENSE.CC-BY-4.0
dochint-1.0.1.dist-info/METADATA
dochint-1.0.1.dist-info/WHEEL
dochint-1.0.1.dist-info/entry_points.txt
dochint-1.0.1.dist-info/top_level.txt
dochint-1.0.1.dist-info/RECORD
