Metadata-Version: 2.4
Name: dochint
Version: 1.0.1
Summary: A macro processor for authoring HTML documents.
Author-email: Maria Nicolae <maria@marianicolae.com>
License-Expression: Apache-2.0 OR CC-BY-4.0
Project-URL: Homepage, https://marianicolae.com/software/dochint/
License-File: LICENSE
License-File: LICENSE.Apache-2.0
License-File: LICENSE.CC-BY-4.0
Requires-Dist: latex2mathml
Requires-Dist: pybtex
Dynamic: license-file
